sweet_sqlasync/__init__.py
sweet_sqlasync/base_model.py
sweet_sqlasync/connections.py
sweet_sqlasync/execute.py
sweet_sqlasync/query.py
sweet_sqlasync/utils.py
sweet_sqlasync-0.0.1b3.dist-info/METADATA
sweet_sqlasync-0.0.1b3.dist-info/WHEEL
sweet_sqlasync-0.0.1b3.dist-info/top_level.txt
sweet_sqlasync-0.0.1b3.dist-info/RECORD
