Metadata-Version: 2.1
Name: sweet-sqlasync
Version: 0.0.1b3
Summary: Syntax sugar for SQLAlchemy + aiopg
Home-page: https://github.com/aCLr/sweet-sqlasync
Author: antonio_antuan
Author-email: a.ch.clr@gmail.com
License: UNKNOWN
Platform: UNKNOWN
Classifier: License :: OSI Approved :: MIT License
Classifier: Programming Language :: Python :: 3
Requires-Python: >=3.7
Requires-Dist: psycopg2 (==2.8.4)
Requires-Dist: aiopg
Requires-Dist: sqlalchemy
